videostream/__init__.py
videostream/client.py
videostream/decoder.py
videostream/frame.py
videostream/host.py
videostream/library.py
videostream-2.1.4.dist-info/licenses/LICENSE
videostream-2.1.4.dist-info/licenses/NOTICE
videostream-2.1.4.dist-info/METADATA
videostream-2.1.4.dist-info/WHEEL
videostream-2.1.4.dist-info/top_level.txt
videostream-2.1.4.dist-info/RECORD
