Metadata-Version: 2.4
Name: videostream
Version: 2.1.4
Summary: Video utility library for embedded Linux with DMA buffer support
Author-email: Au-Zone Technologies <support@au-zone.com>
Maintainer-email: Au-Zone Technologies <support@au-zone.com>
License: Apache-2.0
Project-URL: Homepage, https://github.com/EdgeFirstAI/videostream
Project-URL: Documentation, https://github.com/EdgeFirstAI/videostream#readme
Project-URL: Repository, https://github.com/EdgeFirstAI/videostream.git
Project-URL: Issues, https://github.com/EdgeFirstAI/videostream/issues
Project-URL: Changelog, https://github.com/EdgeFirstAI/videostream/blob/main/CHANGELOG.md
Keywords: video,gstreamer,dma-buf,embedded,computer-vision,edge-ai
Classifier: Development Status :: 4 - Beta
Classifier: Intended Audience :: Developers
Classifier: Operating System :: POSIX :: Linux
Classifier: Programming Language :: Python :: 3
Classifier: Programming Language :: Python :: 3.8
Classifier: Programming Language :: Python :: 3.9
Classifier: Programming Language :: Python :: 3.10
Classifier: Programming Language :: Python :: 3.11
Classifier: Programming Language :: Python :: 3.12
Classifier: Topic :: Multimedia :: Video
Classifier: Topic :: Software Development :: Libraries
Requires-Python: >=3.8
License-File: LICENSE
License-File: NOTICE
Dynamic: license-file
